vdd/__init__.py
vdd/coda/__init__.py
vdd/coda/data/sample_compact.xlsx
vdd/coda/io.py
vdd/coda/models.py
vdd/coda/tests/__init__.py
vdd/coda/tests/data/demo_model.xlsx
vdd/coda/tests/data/demo_model_casestudy1.xlsx
vdd/coda/tests/data/demo_model_compact.xlsx
vdd/coda/tests/test_io.py
vdd/coda/tests/test_models.py
vdd/common/__init__.py
vdd/common/abstract.py
vdd/common/io.py
vdd/common/tests/__init__.py
vdd/common/tests/test_io.py
vdd/docs/google_sheets_api.md
vdd/requirements/__init__.py
vdd/requirements/io.py
vdd/requirements/models.py
vdd/requirements/tests/__init__.py
vdd/requirements/tests/fixtures/case__minimal_example.json
vdd/requirements/tests/fixtures/case__motorcycle_helmet.json
vdd/requirements/tests/fixtures/case__simple_aircraft.json
vdd/requirements/tests/fixtures/minimal_example_blank.json
vdd/requirements/tests/fixtures/minimal_example_custom_label.json
vdd/requirements/tests/fixtures/minimal_example_different_cell_a1.json
vdd/requirements/tests/fixtures/minimal_example_duplicate_requirement.json
vdd/requirements/tests/fixtures/minimal_example_extra_column.json
vdd/requirements/tests/fixtures/minimal_example_extra_row.json
vdd/requirements/tests/fixtures/minimal_example_incomplete_tril.json
vdd/requirements/tests/fixtures/minimal_example_incomplete_triu.json
vdd/requirements/tests/fixtures/minimal_example_misaligned_requirements.json
vdd/requirements/tests/fixtures/minimal_example_populated.json
vdd/requirements/tests/fixtures/minimal_example_score_column.json
vdd/requirements/tests/fixtures/minimal_example_tril_ones.json
vdd/requirements/tests/fixtures/minimal_example_zeros.json
vdd/requirements/tests/test_io.py
vdd/requirements/tests/test_models.py
vdd-2.0.1.dist-info/LICENSE
vdd-2.0.1.dist-info/METADATA
vdd-2.0.1.dist-info/WHEEL
vdd-2.0.1.dist-info/RECORD
