Metadata-Version: 2.1
Name: vdd
Version: 2.0.1
Summary: Tools for Value-Driven Design
License: MIT
Author: Alex Corrie
Author-email: ajccode@gmail.com
Requires-Python: >=3.8,<3.13
Classifier: License :: OSI Approved :: MIT License
Classifier: Programming Language :: Python :: 3
Classifier: Programming Language :: Python :: 3.8
Classifier: Programming Language :: Python :: 3.9
Classifier: Programming Language :: Python :: 3.10
Classifier: Programming Language :: Python :: 3.11
Requires-Dist: numpy (>=1.21.1)
Requires-Dist: openpyxl (>=3.0.10,<4.0.0)
Requires-Dist: pandas (>=1.3.5)
Requires-Dist: platformdirs (>=2.6.2)
Requires-Dist: pygsheets (>=2.0.5,<3.0.0)
Requires-Dist: pytz (>=2022.6)
Requires-Dist: xlrd (>=2.0,<3.0)
